acbox/__init__.py
acbox/clickwrapper.py
acbox/dictionaries.py
acbox/fileops.py
acbox/git.py
acbox/loader.py
acbox/packer.py
acbox/run1.py
acbox/runner.py
acbox/ureporting.py
acbox/utils.py
acbox/cli/__init__.py
acbox/cli/script.py
acbox/cli/shared.py
acbox/cli/flags/__init__.py
acbox/cli/flags/base.py
acbox/cli/flags/logging.py
acbox/cli/parsers/__init__.py
acbox/cli/parsers/base.py
acbox/cli/parsers/parser.py
acbox/cli/parsers/simple.py
acbox/services/__init__.py
acbox/services/git.py
acbox/toolbox/__init__.py
acbox/toolbox/info.py
acbox/toolbox/main.py
acbox/toolbox/replacer.py
acbox-0.0.5.dist-info/METADATA
acbox-0.0.5.dist-info/WHEEL
acbox-0.0.5.dist-info/entry_points.txt
acbox-0.0.5.dist-info/top_level.txt
acbox-0.0.5.dist-info/RECORD
