Metadata-Version: 2.4
Name: acbox
Version: 0.0.5
Summary: Collection of small tools
Author-email: Antonio Cavallo <a.cavallo@cavallinux.eu>
License: MIT
Project-URL: Source, https://github.com/cav71/acbox
Project-URL: Issues, https://github.com/cav71/acbox
Project-URL: Documentation, https://github.com/cav71/acbox
Classifier: Development Status :: 4 - Beta
Classifier: Programming Language :: Python
Classifier: Programming Language :: Python :: 3.10
Classifier: Programming Language :: Python :: 3.11
Classifier: Programming Language :: Python :: 3.12
Classifier: Programming Language :: Python :: 3.13
Classifier: Programming Language :: Python :: 3.14
Requires-Python: >=3.10
Requires-Dist: click
Requires-Dist: cloup
Requires-Dist: filetype
Requires-Dist: rich
Requires-Dist: pyyaml
Provides-Extra: extra
